analytix/__init__.py
analytix/__main__.py
analytix/abc.py
analytix/auth.py
analytix/client.py
analytix/errors.py
analytix/landing.html
analytix/mixins.py
analytix/py.typed
analytix/queries.py
analytix/shard.py
analytix/types.py
analytix/utils.py
analytix/ux.py
analytix/warnings.py
analytix/groups/__init__.py
analytix/groups/groups.py
analytix/reports/__init__.py
analytix/reports/data.py
analytix/reports/features.py
analytix/reports/interfaces.py
analytix/reports/resources.py
analytix/reports/types.py
analytix-5.5.0.dist-info/licenses/LICENSE
tests/__init__.py
tests/conftest.py
tests/test_auth.py
tests/test_groups.py
tests/test_mixins.py
tests/test_shard.py
tests/test_utils.py
analytix-5.5.0.dist-info/METADATA
analytix-5.5.0.dist-info/WHEEL
analytix-5.5.0.dist-info/top_level.txt
analytix-5.5.0.dist-info/RECORD
