Metadata-Version: 2.4
Name: analytix
Version: 5.5.0
Summary: A simple yet powerful SDK for the YouTube Analytics API.
Home-page: https://github.com/parafoxia/analytix
Author: Ethan Henderson
Author-email: ethan.henderson.1998@gmail.com
License: BSD 3-Clause 'New' or 'Revised' License
Project-URL: Documentation, https://parafoxia.github.io/analytix
Project-URL: Source, https://github.com/parafoxia/analytix
Project-URL: Bug Tracker, https://github.com/parafoxia/analytix/issues
Project-URL: CI, https://github.com/parafoxia/analytix/actions
Project-URL: Changelog, https://github.com/parafoxia/analytix/releases
Classifier: Development Status :: 5 - Production/Stable
Classifier: Environment :: Console
Classifier: Intended Audience :: Developers
Classifier: Intended Audience :: End Users/Desktop
Classifier: License :: OSI Approved :: BSD License
Classifier: Natural Language :: English
Classifier: Operating System :: MacOS
Classifier: Operating System :: Microsoft :: Windows
Classifier: Operating System :: OS Independent
Classifier: Operating System :: POSIX
Classifier: Operating System :: Unix
Classifier: Programming Language :: Python :: 3
Classifier: Programming Language :: Python :: 3 :: Only
Classifier: Programming Language :: Python :: 3.8
Classifier: Programming Language :: Python :: 3.9
Classifier: Programming Language :: Python :: 3.10
Classifier: Programming Language :: Python :: 3.11
Classifier: Programming Language :: Python :: 3.12
Classifier: Programming Language :: Python :: 3.13
Classifier: Programming Language :: Python :: Implementation :: CPython
Classifier: Programming Language :: Python :: Implementation :: PyPy
Classifier: Topic :: Internet
Classifier: Topic :: Scientific/Engineering :: Information Analysis
Classifier: Topic :: Utilities
Classifier: Typing :: Typed
Requires-Python: >=3.8.0,<3.15
License-File: LICENSE
Requires-Dist: urllib3<3.0,>=2.2
Dynamic: author
Dynamic: author-email
Dynamic: classifier
Dynamic: description
Dynamic: description-content-type
Dynamic: home-page
Dynamic: license
Dynamic: license-file
Dynamic: project-url
Dynamic: requires-dist
Dynamic: requires-python
Dynamic: summary
